{
  "/files/appcasename2outdir": true,
  "/files/exportconfig/0/0": "",
  "/files/exportconfig/0/1": "",
  "/files/ioin/casename": "",
  "/files/ioin/snakefile": "",
  "/files/ioin/snakemeshname": "",
  "/files/ioin/volumeshname": "",
  "/files/ioout/basenameoutdir": "rsvs3d_",
  "/files/ioout/basenamepattern": "%y%m%dT%H%M%S_",
  "/files/ioout/logginglvl": 2,
  "/files/ioout/outdir": "",
  "/files/ioout/outputlvl": 2,
  "/files/ioout/pathoutdir": "../out",
  "/files/ioout/pathpattern": "Archive_%Y_%m/Day_%y-%m-%d",
  "/files/ioout/pattern": "",
  "/files/ioout/redirectcerr": false,
  "/files/ioout/redirectcout": false,
  "/grid/activegrid": "voxel",
  "/grid/domain/0/0": 0.0,
  "/grid/domain/0/1": 1.0,
  "/grid/domain/1/0": 0.0,
  "/grid/domain/1/1": 1.0,
  "/grid/domain/2/0": 0.0,
  "/grid/domain/2/1": 1.0,
  "/grid/physdomain/0/0": 0.0,
  "/grid/physdomain/0/1": 1.0,
  "/grid/physdomain/1/0": 0.0,
  "/grid/physdomain/1/1": 1.0,
  "/grid/physdomain/2/0": 0.0,
  "/grid/physdomain/2/1": 1.0,
  "/grid/voronoi/distancebox": 0.1,
  "/grid/voronoi/inputpoints/0": 0.0,
  "/grid/voronoi/pointfile": "",
  "/grid/voronoi/snakecoarseness": 0.0,
  "/grid/voronoi/vorosnakelayers": 2,
  "/grid/voxel/gridsizebackground/0": 1,
  "/grid/voxel/gridsizebackground/1": 1,
  "/grid/voxel/gridsizebackground/2": 1,
  "/grid/voxel/gridsizesnake/0": 6,
  "/grid/voxel/gridsizesnake/1": 6,
  "/grid/voxel/gridsizesnake/2": 6,
  "/rsvs/cstfill/active": true,
  "/rsvs/cstfill/fill": 0.5,
  "/rsvs/filefill/active": false,
  "/rsvs/filefill/fill": "",
  "/rsvs/makefill/active": false,
  "/rsvs/makefill/fill": "",
  "/rsvs/solveralgorithm": 0,
  "/snak/arrivaltolerance": 1e-07,
  "/snak/initboundary": 1,
  "/snak/maxsteps": 50,
  "/snak/multiarrivaltolerance": 0.01,
  "/snak/snaxdiststep": 0.9,
  "/snak/snaxtimestep": 0.9
}